sbeditor/__init__.py
sbeditor/common.py
sbeditor/sbeditor.py
sbeditor/sbuild.py
sbeditor-0.0.4.dist-info/METADATA
sbeditor-0.0.4.dist-info/WHEEL
sbeditor-0.0.4.dist-info/top_level.txt
sbeditor-0.0.4.dist-info/RECORD
