Metadata-Version: 2.1
Name: sbeditor
Version: 0.0.4
Summary: A parser for all things sb3
Home-page: https://github.com/FAReTek1/sbeditor
Author: faretek1
Author-email: 
License: MIT
